[
    {
        "job": "Водитель",
        "salary": 144328,
        "id": 4320475,
        "city": "Бишкек",
        "year": 2022,
        "age": 32
    },
    {
        "job": "Программист",
        "salary": 130261,
        "id": 6310826,
        "city": "Скопье",
        "year": 2021,
        "age": 36
    },
    {
        "job": "Учитель",
        "salary": 50137,
        "id": 9492259,
        "city": "Севилья",
        "year": 2022,
        "age": 39
    },
    {
        "job": "Программист",
        "salary": 131794,
        "id": 9747182,
        "city": "Минск",
        "year": 2022,
        "age": 35
    },
    {
        "job": "Инженер",
        "salary": 136807,
        "id": 3388275,
        "city": "Мадрид",
        "year": 2021,
        "age": 30
    },
    {
        "job": "Программист",
        "salary": 53738,
        "id": 4541239,
        "city": "Санкт-Петербург",
        "year": 2022,
        "age": 43
    },
    {
        "job": "Строитель",
        "salary": 140333,
        "id": 4490403,
        "city": "Гранада",
        "year": 2022,
        "age": 41
    },
    {
        "job": "Косметолог",
        "salary": 61257,
        "id": 9095156,
        "city": "Минск",
        "year": 2022,
        "age": 50
    },
    {
        "job": "Психолог",
        "salary": 54544,
        "id": 8952045,
        "city": "Бишкек",
        "year": 2020,
        "age": 45
    },
    {
        "job": "Строитель",
        "salary": 140503,
        "id": 1086680,
        "city": "Афины",
        "year": 2019,
        "age": 47
    },
    {
        "job": "Строитель",
        "salary": 135671,
        "id": 1029774,
        "city": "Тарраса",
        "year": 2019,
        "age": 43
    }
]